__init__.py
embfile/__init__.py
embfile/_embfile.py
embfile/_utils.py
embfile/compression.py
embfile/errors.py
embfile/initializers.py
embfile/registry.py
embfile/types.py
embfile/word_vector.py
embfile/core/__init__.py
embfile/core/_file.py
embfile/core/loaders.py
embfile/core/reader.py
embfile/formats/__init__.py
embfile/formats/bin.py
embfile/formats/txt.py
embfile/formats/vvm.py
embfile-0.1.1.dist-info/AUTHORS.rst
embfile-0.1.1.dist-info/LICENSE
embfile-0.1.1.dist-info/METADATA
embfile-0.1.1.dist-info/WHEEL
embfile-0.1.1.dist-info/top_level.txt
embfile-0.1.1.dist-info/RECORD
