Metadata-Version: 2.1
Name: embfile
Version: 0.1.1
Summary: A package for working with files containing pre-trained word embeddings (aka word vectors).
Home-page: https://github.com/janLuke/embfile
Author: Gianluca Gippetto
Author-email: gianluca.gippetto@gmail.com
License: MIT license
Keywords: embeddings,word vectors,word2vec,nlp,neural networks,deep learning,machine learning
Platform: UNKNOWN
Classifier: Development Status :: 4 - Beta
Classifier: Intended Audience :: Developers
Classifier: License :: OSI Approved :: MIT License
Classifier: Operating System :: Unix
Classifier: Operating System :: POSIX
Classifier: Operating System :: Microsoft :: Windows
Classifier: Programming Language :: Python
Classifier: Programming Language :: Python :: 3.6
Classifier: Programming Language :: Python :: 3.7
Classifier: Programming Language :: Python :: 3.8
Classifier: Programming Language :: Python :: 3.9
Classifier: Programming Language :: Python :: Implementation :: CPython
Classifier: Topic :: Utilities
Requires-Dist: numpy
Requires-Dist: tqdm
Requires-Dist: overrides
Requires-Dist: tabulate
Provides-Extra: dev
Requires-Dist: tox ; extra == 'dev'
Requires-Dist: pytest ; extra == 'dev'
Requires-Dist: pytest-cov ; extra == 'dev'
Requires-Dist: coverage ; extra == 'dev'
Requires-Dist: flake8 ; extra == 'dev'
Requires-Dist: mypy ; extra == 'dev'
Requires-Dist: twine ; extra == 'dev'
Requires-Dist: bump2version ; extra == 'dev'
